terrakio_api/__init__.py
terrakio_api-0.5.23.dist-info/METADATA
terrakio_api-0.5.23.dist-info/WHEEL
terrakio_api-0.5.23.dist-info/RECORD
