Metadata-Version: 2.4
Name: terrakio-api
Version: 0.5.23
Summary: Client version of the terrakio-python-api
Requires-Python: >=3.11
Requires-Dist: terrakio-core==0.5.23
